Metadata-Version: 2.4
Name: bgs_chat_app
Version: 0.0.21
Summary: A Django app to handle the business growth service AI chat backend.
Author-email: Jamie Fox <jamie.fox@digital.trade.gov.uk>
Project-URL: Repository, https://github.com/uktrade/bgs-chat
Classifier: Environment :: Web Environment
Classifier: Framework :: Django
Classifier: Intended Audience :: Developers
Classifier: License :: OSI Approved :: BSD License
Classifier: Operating System :: OS Independent
Classifier: Programming Language :: Python
Classifier: Programming Language :: Python :: 3
Classifier: Programming Language :: Python :: 3 :: Only
